{
  "products": [
    {
      "id": "1766641328523-1",
      "title": "Premium Wireless Noise Cancelling Headphones",
      "category": "Electronics",
      "price": 299.99,
      "rating": 4.7,
      "reviews": 12453,
      "image": "https://images.unsplash.com/photo-1505740420928-5e560c06d30e?w=400&h=400&fit=crop",
      "asin": "B08EXAMPLE1",
      "affiliate": "https://amazon.com/dp/B08EXAMPLE1?tag=temp",
      "badge": "Best Seller",
      "features": [
        "Active Noise Cancellation",
        "30-hour battery life",
        "Premium sound quality",
        "Comfortable fit"
      ],
      "description": "Experience premium audio with advanced noise cancellation technology.",
      "lastUpdated": "2025-12-25T05:42:08.523Z"
    },
    {
      "id": "1766641328523-2",
      "title": "Smart Fitness Watch with Heart Rate Monitor",
      "category": "Health & Fitness",
      "price": 249.99,
      "rating": 4.5,
      "reviews": 8932,
      "image": "https://images.unsplash.com/photo-1523275335684-37898b6baf30?w=400&h=400&fit=crop",
      "asin": "B08EXAMPLE2",
      "affiliate": "https://amazon.com/dp/B08EXAMPLE2?tag=temp",
      "badge": "Trending",
      "features": [
        "Heart rate monitoring",
        "GPS tracking",
        "Water resistant",
        "7-day battery life"
      ],
      "description": "Track your fitness goals with advanced health monitoring.",
      "lastUpdated": "2025-12-25T05:42:08.523Z"
    },
    {
      "id": "1766641328523-3",
      "title": "Ergonomic Office Chair with Lumbar Support",
      "category": "Home & Office",
      "price": 399.99,
      "rating": 4.8,
      "reviews": 15621,
      "image": "https://images.unsplash.com/photo-1580480055273-228ff5388ef8?w=400&h=400&fit=crop",
      "asin": "B08EXAMPLE3",
      "affiliate": "https://amazon.com/dp/B08EXAMPLE3?tag=temp",
      "badge": "Top Rated",
      "features": [
        "Adjustable lumbar support",
        "Breathable mesh back",
        "Height adjustable",
        "Weight capacity: 300 lbs"
      ],
      "description": "Professional ergonomic chair designed for all-day comfort.",
      "lastUpdated": "2025-12-25T05:42:08.523Z"
    }
  ],
  "metadata": {
    "totalProducts": 3,
    "lastUpdated": "2025-12-25T05:42:08.524Z",
    "categories": [
      "Electronics",
      "Health & Fitness",
      "Home & Office"
    ]
  }
}